Chatty-0.2.dist-info/METADATA
Chatty-0.2.dist-info/RECORD
Chatty-0.2.dist-info/WHEEL
Chatty-0.2.dist-info/top_level.txt
chatty/__init__.py
chatty/configuration.py
chatty/exceptions.py
chatty/support.py
chatty/types.py
chatty/bots/__init__.py
chatty/bots/decorator.py
chatty/bots/echo.py
chatty/bots/interface.py
chatty/bots/router.py
chatty/bots/standard.py
chatty/bots/synchronized.py
chatty/sessions/__init__.py
chatty/sessions/echo.py
chatty/sessions/email.py
chatty/sessions/interface.py
chatty/sessions/router.py
chatty/sessions/slack.py
chatty/sessions/tkinter.py
chatty/sessions/xmpp.py
chatty/signals/__init__.py
chatty/signals/delivery_failure.py
chatty/signals/interface.py
chatty/signals/message.py
chatty/signals/metadata.py
chatty/signals/status_change.py
test_chatty/__init__.py
test_chatty/__main__.py
test_chatty/support.py
test_chatty/test_sessions/__init__.py
test_chatty/test_sessions/__main__.py
test_chatty/test_sessions/test_echo.py
test_chatty/test_sessions/test_email.py
test_chatty/test_sessions/test_slack.py
test_chatty/test_sessions/test_tkinter.py
test_chatty/test_sessions/test_xmpp.py
