Metadata-Version: 2.1
Name: Chatty
Version: 0.2
Summary: A multi-platform chat bot framework
Home-page: https://github.com/hosford42/Chatty
Author: Aaron Hosford
Author-email: hosford42@gmail.com
License: MIT
Download-URL: https://pypi.org/project/Chatty
Keywords: chat bot chatbot AI artificial intelligence email xmpp IM message text messaging framework slack session conversation interactive platform multi-platform window local remote protocol
Platform: UNKNOWN
Classifier: Development Status :: 3 - Alpha
Classifier: Intended Audience :: Developers
Classifier: Intended Audience :: Telecommunications Industry
Classifier: License :: OSI Approved :: MIT License
Classifier: Natural Language :: English
Classifier: Operating System :: OS Independent
Classifier: Programming Language :: Python :: 3
Classifier: Topic :: Communications :: Chat
Classifier: Topic :: Communications :: Email
Classifier: Topic :: Internet :: XMPP
Classifier: Topic :: Multimedia
Classifier: Topic :: Scientific/Engineering :: Artificial Intelligence
Classifier: Topic :: Scientific/Engineering :: Human Machine Interfaces
Classifier: Topic :: Software Development :: Libraries :: Application Frameworks
Classifier: Topic :: Software Development :: User Interfaces
Classifier: Topic :: Text Processing :: Linguistic
Provides-Extra: tkinter
Provides-Extra: xmpp
Provides-Extra: slack
